exoSpin/__init__.py
exoSpin/exoplanet_class.py
exoSpin/obliquity.py
exoSpin/pdf_functions.py
exoSpin/plot_class.py
exoSpin-0.3.dist-info/LICENSE
exoSpin-0.3.dist-info/METADATA
exoSpin-0.3.dist-info/WHEEL
exoSpin-0.3.dist-info/top_level.txt
exoSpin-0.3.dist-info/RECORD
